flybase_mcp-0.1.0.dist-info/licenses/LICENSE.txt
flybase_mcp_server/__init__.py
flybase_mcp_server/main.py
flybase_mcp_server/server.py
flybase_mcp_server/data/gene_symbols_fbgn_ids.csv
flybase_mcp-0.1.0.dist-info/METADATA
flybase_mcp-0.1.0.dist-info/WHEEL
flybase_mcp-0.1.0.dist-info/top_level.txt
flybase_mcp-0.1.0.dist-info/RECORD
