Metadata-Version: 2.4
Name: flybase-mcp
Version: 0.1.0
Summary: MCP server for FlyBase
Requires-Python: >=3.11
License-File: LICENSE.txt
Requires-Dist: httpx>=0.28.1
Requires-Dist: mcp[cli]>=1.13.1
Dynamic: license-file
